WhiskiWrap/__init__.py
WhiskiWrap/base.py
WhiskiWrap/default.parameters
WhiskiWrap/halfspace.detectorbank
WhiskiWrap/io.py
WhiskiWrap/line.detectorbank
WhiskiWrap/mfile_io.py
WhiskiWrap/pipeline.py
WhiskiWrap/sensitive.parameters
WhiskiWrap/wfile_io.py
whiskiwrap-1.2.5.dist-info/licenses/LICENSE.txt
wwutils/__init__.py
wwutils/bootstrap.py
wwutils/lock_module.py
wwutils/misc.py
wwutils/plots.py
wwutils/stats.py
wwutils/utils.py
wwutils/whisk_permissions.py
wwutils/whiskerpad.py
wwutils/classifiers/reclassify.py
wwutils/classifiers/train_unet.py
wwutils/classifiers/unet_classifier.py
wwutils/data_manip/combine_sides.py
wwutils/data_manip/combine_whisker_files.py
wwutils/data_manip/load_data.py
wwutils/data_manip/load_ffmpeg_lib_example.py
wwutils/video_utils/create_video_whiski.py
wwutils/video_utils/extract_video_segments.py
wwutils/video_utils/video.py
whiskiwrap-1.2.5.dist-info/METADATA
whiskiwrap-1.2.5.dist-info/WHEEL
whiskiwrap-1.2.5.dist-info/top_level.txt
whiskiwrap-1.2.5.dist-info/RECORD
