Metadata-Version: 2.4
Name: WhiskiWrap
Version: 1.2.5
Summary: Whisk package wrapper created by Chris Rodgers, maintained by Vincent Prevosto
Home-page: http://pypi.python.org/pypi/WhiskiWrap/
Author: Chris Rodgers, Ariel Iporre, Vincent Prevosto
Author-email: 
Maintainer: vncntprvst
License: The Janelia Farm Research Campus Software Copyright 1.1
Project-URL: Homepage, http://pypi.python.org/pypi/WhiskiWrap/
Requires-Python: >=3.10
License-File: LICENSE.txt
Requires-Dist: tables>=3.5.1
Requires-Dist: pandas
Requires-Dist: MediaInfo
Requires-Dist: future
Requires-Dist: tifffile
Requires-Dist: imagecodecs
Requires-Dist: statsmodels
Requires-Dist: ffmpeg-python>=0.2.0
Requires-Dist: whisk-janelia[ffmpeg]
Requires-Dist: zarr
Requires-Dist: pyarrow
Requires-Dist: matplotlib
Requires-Dist: easygui
Requires-Dist: opencv-python
Requires-Dist: h5py
Requires-Dist: seaborn
Requires-Dist: plotly
Requires-Dist: psutil
Requires-Dist: cmcrameri
Dynamic: home-page
Dynamic: license-file
Dynamic: requires-python
